[
    {
      "countryName": "USA",
      "cityName": "New York",
      "subcity": "Manhattan",
      "category": "Jobs",
      "subCategory": "Software Development",
      "title": "Full Stack Developer Needed",
      "postingBody": "We are looking for a skilled Full Stack Developer to join our team. Must have experience with React and Node.js.",
      "email": "hr@techcorp.com",
      "phone": "123-456-7890",
      "sex": "Any",
      "age": "25-40",
      "postList": ["1-2 years experience", "Bachelor's degree in Computer Science"],
      "featuredAd": true,
      "extendedAd": false
    },
    {
      "countryName": "Canada",
      "cityName": "Toronto",
      "subcity": "Downtown",
      "category": "Services",
      "subCategory": "Home Repair",
      "title": "Expert Plumber Available",
      "postingBody": "Offering professional plumbing services in the Toronto area. Over 10 years of experience.",
      "email": "plumber.joe@example.com",
      "phone": "234-567-8901",
      "sex": "Male",
      "age": "30",
      "postList": ["Emergency services available", "Free estimates"],
      "featuredAd": false,
      "extendedAd": true
    },
    {
      "countryName": "UK",
      "cityName": "London",
      "subcity": "Camden",
      "category": "Housing",
      "subCategory": "Apartments for Rent",
      "title": "Spacious 2 Bedroom Apartment",
      "postingBody": "A lovely 2 bedroom apartment located in Camden. Close to public transport and local amenities.",
      "email": "rentals@londonliving.co.uk",
      "phone": "345-678-9012",
      "sex": "Any",
      "age": "N/A",
      "postList": ["No pets", "1 year lease minimum"],
      "featuredAd": true,
      "extendedAd": true
    },
    {
      "countryName": "Australia",
      "cityName": "Sydney",
      "subcity": "Bondi",
      "category": "Community",
      "subCategory": "Events",
      "title": "Beach Cleanup Volunteer Event",
      "postingBody": "Join us for a beach cleanup event at Bondi Beach. Help us keep our beaches clean and beautiful.",
      "email": "volunteer@beachcleanup.org",
      "phone": "456-789-0123",
      "sex": "Any",
      "age": "18+",
      "postList": ["Bring gloves and sunscreen", "Snacks provided"],
      "featuredAd": false,
      "extendedAd": false
    },
    {
      "countryName": "Germany",
      "cityName": "Berlin",
      "subcity": "Kreuzberg",
      "category": "For Sale",
      "subCategory": "Electronics",
      "title": "Used MacBook Pro 2019",
      "postingBody": "Selling a used MacBook Pro 2019 in excellent condition. 16GB RAM, 512GB SSD.",
      "email": "techsales@berlinmarket.de",
      "phone": "567-890-1234",
      "sex": "Any",
      "age": "19",
      "postList": ["Price negotiable", "Pickup only"],
      "featuredAd": true,
      "extendedAd": false
    }
  ]
  